sortphotos-1.0.1.dist-info/METADATA
sortphotos-1.0.1.dist-info/RECORD
sortphotos-1.0.1.dist-info/WHEEL
sortphotos-1.0.1.dist-info/entry_points.txt
sortphotos-1.0.1.dist-info/top_level.txt
src/__init__.py
src/sortphotos.py
src/Image-ExifTool/Changes
src/Image-ExifTool/README
src/Image-ExifTool/exiftool
src/Image-ExifTool/lib/File/RandomAccess.pm
src/Image-ExifTool/lib/File/RandomAccess.pod
src/Image-ExifTool/lib/Image/ExifTool.pm
src/Image-ExifTool/lib/Image/ExifTool.pod
src/Image-ExifTool/lib/Image/ExifTool/AES.pm
src/Image-ExifTool/lib/Image/ExifTool/AFCP.pm
src/Image-ExifTool/lib/Image/ExifTool/AIFF.pm
src/Image-ExifTool/lib/Image/ExifTool/APE.pm
src/Image-ExifTool/lib/Image/ExifTool/APP12.pm
src/Image-ExifTool/lib/Image/ExifTool/ASF.pm
src/Image-ExifTool/lib/Image/ExifTool/Apple.pm
src/Image-ExifTool/lib/Image/ExifTool/BMP.pm
src/Image-ExifTool/lib/Image/ExifTool/BZZ.pm
src/Image-ExifTool/lib/Image/ExifTool/BigTIFF.pm
src/Image-ExifTool/lib/Image/ExifTool/BuildTagLookup.pm
src/Image-ExifTool/lib/Image/ExifTool/Canon.pm
src/Image-ExifTool/lib/Image/ExifTool/CanonCustom.pm
src/Image-ExifTool/lib/Image/ExifTool/CanonRaw.pm
src/Image-ExifTool/lib/Image/ExifTool/CanonVRD.pm
src/Image-ExifTool/lib/Image/ExifTool/CaptureOne.pm
src/Image-ExifTool/lib/Image/ExifTool/Casio.pm
src/Image-ExifTool/lib/Image/ExifTool/Charset.pm
src/Image-ExifTool/lib/Image/ExifTool/DICOM.pm
src/Image-ExifTool/lib/Image/ExifTool/DNG.pm
src/Image-ExifTool/lib/Image/ExifTool/DPX.pm
src/Image-ExifTool/lib/Image/ExifTool/DV.pm
src/Image-ExifTool/lib/Image/ExifTool/DarwinCore.pm
src/Image-ExifTool/lib/Image/ExifTool/DjVu.pm
src/Image-ExifTool/lib/Image/ExifTool/EXE.pm
src/Image-ExifTool/lib/Image/ExifTool/Exif.pm
src/Image-ExifTool/lib/Image/ExifTool/FLAC.pm
src/Image-ExifTool/lib/Image/ExifTool/FLIR.pm
src/Image-ExifTool/lib/Image/ExifTool/Fixup.pm
src/Image-ExifTool/lib/Image/ExifTool/Flash.pm
src/Image-ExifTool/lib/Image/ExifTool/FlashPix.pm
src/Image-ExifTool/lib/Image/ExifTool/Font.pm
src/Image-ExifTool/lib/Image/ExifTool/FotoStation.pm
src/Image-ExifTool/lib/Image/ExifTool/FujiFilm.pm
src/Image-ExifTool/lib/Image/ExifTool/GE.pm
