Metadata-Version: 2.1
Name: sortphotos
Version: 1.0.1
Summary: Organizes photos and videos into folders using date/time information 
Home-page: UNKNOWN
Author: Andrew Ning
Author-email: UNKNOWN
License: MIT License
Platform: UNKNOWN
